resoto_plugin_digitalocean/__init__.py
resoto_plugin_digitalocean/client.py
resoto_plugin_digitalocean/collector.py
resoto_plugin_digitalocean/config.py
resoto_plugin_digitalocean/resources.py
resoto_plugin_digitalocean/utils.py
test/__init__.py
test/test_collector.py
test/test_config.py
test/fixtures/__init__.py
test/fixtures/alerts.py
test/fixtures/apps.py
test/fixtures/cdns.py
test/fixtures/certificates.py
test/fixtures/cpu_metrics.py
test/fixtures/databases.py
test/fixtures/domain_records.py
test/fixtures/domains.py
test/fixtures/droplets.py
test/fixtures/firewalls.py
test/fixtures/floatingip.py
test/fixtures/k8s.py
test/fixtures/loadbalancers.py
test/fixtures/memory_available.py
test/fixtures/neighbor_ids.py
test/fixtures/projectresources.py
test/fixtures/projects.py
test/fixtures/regions.py
test/fixtures/registry.py
test/fixtures/registry_repositories.py
test/fixtures/registry_repository_tags.py
test/fixtures/snapshots.py
test/fixtures/spaces.py
test/fixtures/ssh_keys.py
test/fixtures/tags.py
test/fixtures/volumes.py
test/fixtures/vpcs.py
resoto_plugin_digitalocean-3.9.0.dist-info/METADATA
resoto_plugin_digitalocean-3.9.0.dist-info/WHEEL
resoto_plugin_digitalocean-3.9.0.dist-info/entry_points.txt
resoto_plugin_digitalocean-3.9.0.dist-info/top_level.txt
resoto_plugin_digitalocean-3.9.0.dist-info/RECORD
