Metadata-Version: 2.1
Name: resoto-plugin-digitalocean
Version: 3.9.0
Summary: Resoto DigitalOcean Collector Plugin
Author: Some Engineering Inc.
License: AGPLv3
Project-URL: Documentation, https://resoto.com
Project-URL: Source, https://github.com/someengineering/resoto/tree/main/plugins/digitalocean
Classifier: Development Status :: 5 - Production/Stable
Classifier: Intended Audience :: System Administrators
Classifier: Intended Audience :: Information Technology
Classifier: License :: OSI Approved :: GNU Affero General Public License v3 or later (AGPLv3+)
Classifier: Programming Language :: Python :: 3.9
Classifier: Operating System :: POSIX :: Linux
Classifier: Operating System :: Unix
Classifier: Environment :: Console
Classifier: Natural Language :: English
Classifier: Topic :: Security
Classifier: Topic :: Utilities
Requires-Python: >=3.9
Requires-Dist: resotolib ==3.9.0
Requires-Dist: boto3
Requires-Dist: requests
Requires-Dist: botocore
Requires-Dist: retrying
Provides-Extra: test
Requires-Dist: mypy ; extra == 'test'
Requires-Dist: tzlocal ; extra == 'test'
